simplesocket/__init__.py
simplesocket/simplesocket.py
simplesocket-0.3.dist-info/METADATA
simplesocket-0.3.dist-info/RECORD
simplesocket-0.3.dist-info/WHEEL
simplesocket-0.3.dist-info/top_level.txt
