Metadata-Version: 2.1
Name: simplesocket
Version: 0.3
Summary: simple implementation of python socket for creating server/client based programs supporting threading.
Home-page: https://github.com/aasmpro/simplesocket
Author: Abolfazl Amiri
Author-email: aa.smpro@gmail.com
License: UNKNOWN
Platform: UNKNOWN
Classifier: License :: OSI Approved :: GNU General Public License v3 (GPLv3)
Classifier: Operating System :: OS Independent
Classifier: Programming Language :: Python :: 3
Classifier: Programming Language :: Python :: 3.5
Classifier: Programming Language :: Python :: 3.6
Classifier: Programming Language :: Python :: 3.7
Classifier: Programming Language :: Python :: 3 :: Only
